{
    "Date": "2020-09-25T11:30:00+03:00",
    "PreviousDate": "2020-09-24T11:30:00+03:00",
    "PreviousURL": "\/\/www.cbr-xml-daily.ru\/archive\/2020\/09\/24\/daily_json.js",
    "Timestamp": "2020-09-24T23:00:00+03:00",
    "Valute": {
        "AUD": {
            "ID": "R01010",
            "NumCode": "036",
            "CharCode": "AUD",
            "Nominal": 1,
            "Name": "Австралийский доллар",
            "Value": 54.3719,
            "Previous": 54.311
        },
        "AZN": {
            "ID": "R01020A",
            "NumCode": "944",
            "CharCode": "AZN",
            "Nominal": 1,
            "Name": "Азербайджанский манат",
            "Value": 45.4255,
            "Previous": 44.9408
        },
        "GBP": {
            "ID": "R01035",
            "NumCode": "826",
            "CharCode": "GBP",
            "Nominal": 1,
            "Name": "Фунт стерлингов Соединенного королевства",
            "Value": 98.2244,
            "Previous": 96.8022
        },
        "AMD": {
            "ID": "R01060",
            "NumCode": "051",
            "CharCode": "AMD",
            "Nominal": 100,
            "Name": "Армянских драмов",
            "Value": 15.8737,
            "Previous": 15.7237
        },
        "BYN": {
            "ID": "R01090B",
            "NumCode": "933",
            "CharCode": "BYN",
            "Nominal": 1,
            "Name": "Белорусский рубль",
            "Value": 29.6189,
            "Previous": 29.4725
        },
        "BGN": {
            "ID": "R01100",
            "NumCode": "975",
            "CharCode": "BGN",
            "Nominal": 1,
            "Name": "Болгарский лев",
            "Value": 46.0105,
            "Previous": 45.612
        },
        "BRL": {
            "ID": "R01115",
            "NumCode": "986",
            "CharCode": "BRL",
            "Nominal": 1,
            "Name": "Бразильский реал",
            "Value": 13.798,
            "Previous": 13.9539
        },
        "HUF": {
            "ID": "R01135",
            "NumCode": "348",
            "CharCode": "HUF",
            "Nominal": 100,
            "Name": "Венгерских форинтов",
            "Value": 24.6485,
            "Previous": 24.5154
        },
        "HKD": {
            "ID": "R01200",
            "NumCode": "344",
            "CharCode": "HKD",
            "Nominal": 10,
            "Name": "Гонконгских долларов",
            "Value": 99.5819,
            "Previous": 98.5219
        },
        "DKK": {
            "ID": "R01215",
            "NumCode": "208",
            "CharCode": "DKK",
            "Nominal": 1,
            "Name": "Датская крона",
            "Value": 12.0906,
            "Previous": 11.9873
        },
        "USD": {
            "ID": "R01235",
            "NumCode": "840",
            "CharCode": "USD",
            "Nominal": 1,
            "Name": "Доллар США",
            "Value": 77.178,
            "Previous": 76.3545
        },
        "EUR": {
            "ID": "R01239",
            "NumCode": "978",
            "CharCode": "EUR",
            "Nominal": 1,
            "Name": "Евро",
            "Value": 89.9818,
            "Previous": 89.2508
        },
        "INR": {
            "ID": "R01270",
            "NumCode": "356",
            "CharCode": "INR",
            "Nominal": 10,
            "Name": "Индийских рупий",
            "Value": 10.4422,
            "Previous": 10.3792
        },
        "KZT": {
            "ID": "R01335",
            "NumCode": "398",
            "CharCode": "KZT",
            "Nominal": 100,
            "Name": "Казахстанских тенге",
            "Value": 18.0664,
            "Previous": 17.9472
        },
        "CAD": {
            "ID": "R01350",
            "NumCode": "124",
            "CharCode": "CAD",
            "Nominal": 1,
            "Name": "Канадский доллар",
            "Value": 57.5998,
            "Previous": 57.263
        },
        "KGS": {
            "ID": "R01370",
            "NumCode": "417",
            "CharCode": "KGS",
            "Nominal": 100,
            "Name": "Киргизских сомов",
            "Value": 97.2311,
            "Previous": 96.2959
        },
        "CNY": {
            "ID": "R01375",
            "NumCode": "156",
            "CharCode": "CNY",
            "Nominal": 1,
            "Name": "Китайский юань",
            "Value": 11.3091,
            "Previous": 11.2423
        },
        "MDL": {
            "ID": "R01500",
            "NumCode": "498",
            "CharCode": "MDL",
            "Nominal": 10,
            "Name": "Молдавских леев",
            "Value": 45.953,
            "Previous": 45.6393
        },
        "NOK": {
            "ID": "R01535",
            "NumCode": "578",
            "CharCode": "NOK",
            "Nominal": 10,
            "Name": "Норвежских крон",
            "Value": 80.7166,
            "Previous": 81.2913
        },
        "PLN": {
            "ID": "R01565",
            "NumCode": "985",
            "CharCode": "PLN",
            "Nominal": 1,
            "Name": "Польский злотый",
            "Value": 19.8933,
            "Previous": 19.8396
        },
        "RON": {
            "ID": "R01585F",
            "NumCode": "946",
            "CharCode": "RON",
            "Nominal": 1,
            "Name": "Румынский лей",
            "Value": 18.4716,
            "Previous": 18.3403
        },
        "XDR": {
            "ID": "R01589",
            "NumCode": "960",
            "CharCode": "XDR",
            "Nominal": 1,
            "Name": "СДР (специальные права заимствования)",
            "Value": 108.6473,
            "Previous": 107.8026
        },
        "SGD": {
            "ID": "R01625",
            "NumCode": "702",
            "CharCode": "SGD",
            "Nominal": 1,
            "Name": "Сингапурский доллар",
            "Value": 56.1295,
            "Previous": 55.8514
        },
        "TJS": {
            "ID": "R01670",
            "NumCode": "972",
            "CharCode": "TJS",
            "Nominal": 10,
            "Name": "Таджикских сомони",
            "Value": 74.7849,
            "Previous": 73.9869
        },
        "TRY": {
            "ID": "R01700J",
            "NumCode": "949",
            "CharCode": "TRY",
            "Nominal": 1,
            "Name": "Турецкая лира",
            "Value": 10.0161,
            "Previous": 99.4134
        },
        "TMT": {
            "ID": "R01710A",
            "NumCode": "934",
            "CharCode": "TMT",
            "Nominal": 1,
            "Name": "Новый туркменский манат",
            "Value": 22.0824,
            "Previous": 21.8468
        },
        "UZS": {
            "ID": "R01717",
            "NumCode": "860",
            "CharCode": "UZS",
            "Nominal": 10000,
            "Name": "Узбекских сумов",
            "Value": 75.1636,
            "Previous": 74.3616
        },
        "UAH": {
            "ID": "R01720",
            "NumCode": "980",
            "CharCode": "UAH",
            "Nominal": 10,
            "Name": "Украинских гривен",
            "Value": 27.3165,
            "Previous": 27.0852
        },
        "CZK": {
            "ID": "R01760",
            "NumCode": "203",
            "CharCode": "CZK",
            "Nominal": 10,
            "Name": "Чешских крон",
            "Value": 33.3152,
            "Previous": 33.0911
        },
        "SEK": {
            "ID": "R01770",
            "NumCode": "752",
            "CharCode": "SEK",
            "Nominal": 10,
            "Name": "Шведских крон",
            "Value": 85.2155,
            "Previous": 85.4201
        },
        "CHF": {
            "ID": "R01775",
            "NumCode": "756",
            "CharCode": "CHF",
            "Nominal": 1,
            "Name": "Швейцарский франк",
            "Value": 83.4357,
            "Previous": 82.9219
        },
        "ZAR": {
            "ID": "R01810",
            "NumCode": "710",
            "CharCode": "ZAR",
            "Nominal": 10,
            "Name": "Южноафриканских рэндов",
            "Value": 45.022,
            "Previous": 44.9379
        },
        "KRW": {
            "ID": "R01815",
            "NumCode": "410",
            "CharCode": "KRW",
            "Nominal": 1000,
            "Name": "Вон Республики Корея",
            "Value": 65.748,
            "Previous": 65.6415
        },
        "JPY": {
            "ID": "R01820",
            "NumCode": "392",
            "CharCode": "JPY",
            "Nominal": 100,
            "Name": "Японских иен",
            "Value": 73.2691,
            "Previous": 72.6805
        }
    }
}